{
  "sections": {
    "f96b8e1b-0fd4-4c65-856c-cdd01fe228cc": {
      "type": "banner",
      "blocks": {
        "template--18730720428336__f96b8e1b-0fd4-4c65-856c-cdd01fe228cc-1681420271694828b0-0": {
          "type": "heading",
          "settings": {
            "content": "Disposables is ons vak"
          }
        },
        "template--18730720428336__f96b8e1b-0fd4-4c65-856c-cdd01fe228cc-1681420271694828b0-2": {
          "type": "buttons",
          "settings": {
            "button_color": "btn",
            "button_label": "Bekijk assortiment",
            "button_url": "shopify:\/\/collections\/all",
            "secondary_button_color": "btn btn--tertiary",
            "secondary_button_label": "",
            "secondary_button_url": ""
          }
        },
        "template--18730720428336__f96b8e1b-0fd4-4c65-856c-cdd01fe228cc-1681420271694828b0-1": {
          "type": "content",
          "settings": {
            "content": "<p>De Jong Disposables is een toonaangevende en innoverende importeur en leverancier van disposables, voor uiteenlopende sectoren. Denk aan de food-sector, attractieparken, bioscopen, fastfood outlets, sportkantines, hotels en grootschalige evenementen. Hierbij is een eigen bedrukking ook mogelijk.<\/p>"
          }
        }
      },
      "block_order": [
        "template--18730720428336__f96b8e1b-0fd4-4c65-856c-cdd01fe228cc-1681420271694828b0-0",
        "template--18730720428336__f96b8e1b-0fd4-4c65-856c-cdd01fe228cc-1681420271694828b0-2",
        "template--18730720428336__f96b8e1b-0fd4-4c65-856c-cdd01fe228cc-1681420271694828b0-1"
      ],
      "settings": {
        "image_background_desktop": "shopify:\/\/shop_images\/banner_77ea9b03-015c-4f60-a2d5-1b397e574669.png",
        "show_entire_image": false,
        "enable_lazy_loading": true,
        "show_video_background_mobile": true,
        "color_scheme": "color__bg-primary color__primary",
        "color_text": "",
        "color_border": "color__border-divider-1",
        "enable_gradient": false,
        "style_border": "border--b-width",
        "layout_y_spacing": "min-h-[350px] md:min-h-[450px]",
        "layout_y_alignment": "items-end",
        "layout_x_alignment": "justify-center text-center",
        "visibility": ""
      }
    },
    "2cb9d59b-242d-48e7-821a-ae61144186e8": {
      "type": "content-grid",
      "blocks": {
        "template--20644271554834__2cb9d59b-242d-48e7-821a-ae61144186e8-content-1": {
          "type": "content",
          "settings": {
            "heading": "Bekijk onze frietbakjes",
            "content": "<p>Zie hier ons brede assortiment aan frietbakjes<\/p>",
            "button_label": "Shop Frietbakjes",
            "button_url": "shopify:\/\/collections\/frietbakjes",
            "full_block_link": false,
            "image_featured": "shopify:\/\/shop_images\/image-3-col.png",
            "enable_autoplay": true,
            "enable_mute_toggle": true,
            "enable_loop": true,
            "spacing_top": 0,
            "spacing_bottom": 0,
            "enable_padding": true,
            "color_scheme": "color__bg-body color__text",
            "color_border": "color__border-divider-1",
            "color_text": "color__text",
            "color_button": "btn",
            "enable_gradient": false,
            "layout_y_alignment": "items-end content-end",
            "layout_x_alignment": "",
            "layout_row_span": "row-span-1",
            "layout_col_span": "col-span-1 md: md:col-span-1"
          }
        },
        "template--20644271554834__2cb9d59b-242d-48e7-821a-ae61144186e8-content-2": {
          "type": "content",
          "settings": {
            "heading": "Bekijk onze pizzadozen",
            "content": "<p>Zie hier onze brede assortiment aan pizzadozen<\/p>",
            "button_label": "Shop Pizzadozen",
            "button_url": "shopify:\/\/collections\/all",
            "full_block_link": false,
            "image_featured": "shopify:\/\/shop_images\/image-3-col2.png",
            "enable_autoplay": true,
            "enable_mute_toggle": true,
            "enable_loop": true,
            "spacing_top": 0,
            "spacing_bottom": 0,
            "enable_padding": true,
            "color_scheme": "color__bg-body color__text",
            "color_border": "color__border-divider-1",
            "color_text": "color__text",
            "color_button": "btn",
            "enable_gradient": false,
            "layout_y_alignment": "items-end content-end",
            "layout_x_alignment": "",
            "layout_row_span": "row-span-1",
            "layout_col_span": "col-span-1 md: md:col-span-1"
          }
        },
        "template--20644271554834__2cb9d59b-242d-48e7-821a-ae61144186e8-content-3": {
          "type": "content",
          "settings": {
            "heading": "Bekijk onze foodtrays",
            "content": "<p>Zie hier ons brede assortiment aan  foodtrays <\/p>",
            "button_label": "Shop Foodtrays",
            "button_url": "shopify:\/\/collections\/all",
            "full_block_link": false,
            "image_featured": "shopify:\/\/shop_images\/image-3-col3.png",
            "enable_autoplay": true,
            "enable_mute_toggle": true,
            "enable_loop": true,
            "spacing_top": 0,
            "spacing_bottom": 0,
            "enable_padding": true,
            "color_scheme": "color__bg-body color__text",
            "color_border": "color__border-divider-1",
            "color_text": "color__text",
            "color_button": "btn",
            "enable_gradient": false,
            "layout_y_alignment": "items-end content-end",
            "layout_x_alignment": "",
            "layout_row_span": "row-span-1",
            "layout_col_span": "col-span-1 md: md:col-span-1"
          }
        }
      },
      "block_order": [
        "template--20644271554834__2cb9d59b-242d-48e7-821a-ae61144186e8-content-1",
        "template--20644271554834__2cb9d59b-242d-48e7-821a-ae61144186e8-content-2",
        "template--20644271554834__2cb9d59b-242d-48e7-821a-ae61144186e8-content-3"
      ],
      "settings": {
        "heading": "",
        "content": "<p><\/p><p><\/p>",
        "button_label": "",
        "button_url": "",
        "spacing_top": 100,
        "spacing_bottom": 100,
        "color_scheme": "color__bg-body color__text",
        "color_border": "color__border-divider-1",
        "color_button": "btn btn--secondary",
        "style_border": "border--b-width",
        "row_size_desktop": "md:grid-cols-3",
        "row_size_mobile": "grid-cols-1",
        "layout_x_alignment": "justify-between",
        "visibility": ""
      }
    },
    "0aee11fe-16ff-4cae-924b-b6dc71c8827b": {
      "type": "content-grid",
      "blocks": {
        "template--20644271554834__0aee11fe-16ff-4cae-924b-b6dc71c8827b-content-1": {
          "type": "content",
          "settings": {
            "heading": "Disposables is ons vak",
            "content": "<p>Zie hier ons assortiment aan verschillende kartonnen rietjes<\/p>",
            "button_label": "Shop Ritjes",
            "button_url": "shopify:\/\/collections\/rietjes",
            "full_block_link": false,
            "image_featured": "shopify:\/\/shop_images\/img-2col-1.png",
            "enable_autoplay": true,
            "enable_mute_toggle": true,
            "enable_loop": true,
            "spacing_top": 0,
            "spacing_bottom": 0,
            "enable_padding": true,
            "color_scheme": "color__bg-body color__text",
            "color_border": "color__border-divider-1",
            "color_text": "color__text",
            "color_button": "btn",
            "enable_gradient": false,
            "layout_y_alignment": "items-end content-end",
            "layout_x_alignment": "",
            "layout_row_span": "row-span-1",
            "layout_col_span": "col-span-1 md: md:col-span-1"
          }
        },
        "template--20644271554834__0aee11fe-16ff-4cae-924b-b6dc71c8827b-content-2": {
          "type": "content",
          "settings": {
            "heading": "Disposables is ons vak",
            "content": "<p>Lorem ipsum dolor sit amet, consectetur adipiscing elit, sed<\/p>",
            "button_label": "Shop Clear Cups",
            "button_url": "shopify:\/\/collections\/clear-cups",
            "full_block_link": false,
            "image_featured": "shopify:\/\/shop_images\/img-2col-2.png",
            "enable_autoplay": true,
            "enable_mute_toggle": true,
            "enable_loop": true,
            "spacing_top": 0,
            "spacing_bottom": 0,
            "enable_padding": true,
            "color_scheme": "color__bg-body color__text",
            "color_border": "color__border-divider-1",
            "color_text": "color__text",
            "color_button": "btn",
            "enable_gradient": false,
            "layout_y_alignment": "items-end content-end",
            "layout_x_alignment": "",
            "layout_row_span": "row-span-1",
            "layout_col_span": "col-span-1 md: md:col-span-1"
          }
        },
        "template--20644271554834__0aee11fe-16ff-4cae-924b-b6dc71c8827b-content-3": {
          "type": "content",
          "settings": {
            "heading": "",
            "content": "",
            "button_label": "",
            "button_url": "shopify:\/\/collections\/milkshake-bekers",
            "full_block_link": true,
            "image_featured": "shopify:\/\/shop_images\/img-1col.png",
            "enable_autoplay": true,
            "enable_mute_toggle": true,
            "enable_loop": true,
            "spacing_top": 0,
            "spacing_bottom": 0,
            "enable_padding": true,
            "color_scheme": "color__bg-body color__text",
            "color_border": "!color__border-transparent",
            "color_text": "color__text",
            "color_button": "btn btn--plain",
            "enable_gradient": false,
            "layout_y_alignment": "items-end content-end",
            "layout_x_alignment": "",
            "layout_row_span": "row-span-1",
            "layout_col_span": "col-span-1 md: md:col-span-2"
          }
        }
      },
      "block_order": [
        "template--20644271554834__0aee11fe-16ff-4cae-924b-b6dc71c8827b-content-1",
        "template--20644271554834__0aee11fe-16ff-4cae-924b-b6dc71c8827b-content-2",
        "template--20644271554834__0aee11fe-16ff-4cae-924b-b6dc71c8827b-content-3"
      ],
      "settings": {
        "heading": "Disposables is ons vak",
        "content": "<p>Duurzame disposables zijn in deze huidige tijd “natuurlijk” niet meer weg te denken, het is een thema die hoog op onze agenda staat. Ons uitgebreide duurzame disposable assortiment is wederom een serie topproducten dat niet te vergelijken is met de traditionele disposables. Het programma is uitgevoerd in een stevige kwaliteit papier, karton en suikerriet (bagasse). Daarnaast bevat ons assortiment een serie duurzaam bestek zoals, bamboe snack vorkjes en ijslepeltjes.<br\/><br\/>De meeste producten zijn gemaakt van volledig hernieuwbare grondstoffen, die volledig composteerbaar zijn. Met deze milieuvriendelijke disposables zetten wij een nieuwe standaard voor kwaliteit en duurzaamheid.<br\/><\/p>",
        "button_label": "",
        "button_url": "shopify:\/\/collections\/clear-cups",
        "spacing_top": 100,
        "spacing_bottom": 100,
        "color_scheme": "color__bg-body color__text",
        "color_border": "color__border-divider-1",
        "color_button": "btn",
        "style_border": "border--b-width",
        "row_size_desktop": "md:grid-cols-2",
        "row_size_mobile": "grid-cols-1",
        "layout_x_alignment": "text-center justify-center flex-col items-center",
        "visibility": ""
      }
    },
    "1e9b6aa9-2f3a-4ca0-a7b2-65d5c9c14d5f": {
      "type": "content-grid",
      "blocks": {
        "template--20644271554834__1e9b6aa9-2f3a-4ca0-a7b2-65d5c9c14d5f-content-1": {
          "type": "content",
          "settings": {
            "heading": "",
            "content": "",
            "button_label": "Button",
            "button_url": "",
            "full_block_link": true,
            "image_featured": "shopify:\/\/shop_images\/img-2col-box-1.png",
            "enable_autoplay": true,
            "enable_mute_toggle": true,
            "enable_loop": true,
            "spacing_top": 0,
            "spacing_bottom": 0,
            "enable_padding": true,
            "color_scheme": "color__bg-body color__text",
            "color_border": "!color__border-transparent",
            "color_text": "color__text",
            "color_button": "btn",
            "enable_gradient": false,
            "layout_y_alignment": "items-end content-end",
            "layout_x_alignment": "",
            "layout_row_span": "row-span-1",
            "layout_col_span": "col-span-1 md: md:col-span-1"
          }
        },
        "template--20644271554834__1e9b6aa9-2f3a-4ca0-a7b2-65d5c9c14d5f-content-3": {
          "type": "content",
          "settings": {
            "heading": "",
            "content": "",
            "button_label": "",
            "button_url": "shopify:\/\/collections\/disposables-bedrukken",
            "full_block_link": true,
            "image_featured": "shopify:\/\/shop_images\/img-2col-box-2.png",
            "enable_autoplay": true,
            "enable_mute_toggle": true,
            "enable_loop": true,
            "spacing_top": 0,
            "spacing_bottom": 0,
            "enable_padding": true,
            "color_scheme": "color__bg-body color__text",
            "color_border": "!color__border-transparent",
            "color_text": "color__text",
            "color_button": "btn btn--plain",
            "enable_gradient": false,
            "layout_y_alignment": "items-end content-end",
            "layout_x_alignment": "",
            "layout_row_span": "row-span-1",
            "layout_col_span": "col-span-1 md: md:col-span-1"
          }
        }
      },
      "block_order": [
        "template--20644271554834__1e9b6aa9-2f3a-4ca0-a7b2-65d5c9c14d5f-content-1",
        "template--20644271554834__1e9b6aa9-2f3a-4ca0-a7b2-65d5c9c14d5f-content-3"
      ],
      "settings": {
        "heading": "Disposables bedrukken",
        "content": "<p>Wilt u disposables bedrukken? De Jong Disposables onderscheidt zich binnen deze markt vooral door het aanbieden van het bedrukken van disposables, waarbij voor iedere klant een passend producten pakket wordt samengesteld.<br\/><br\/>Vaak worden deze disposables voorzien van een eigen bedrukking en indien er geen passend product voor handen is, kan dit speciaal ontwikkeld worden.<br\/><br\/>Praktisch al onze disposables zijn te voorzien van uw logo of design, voor alle mogelijkheden nodigen wij u graag uit bij ons op de showroom in Tynaarlo.<\/p>",
        "button_label": "",
        "button_url": "shopify:\/\/collections\/disposables-bedrukken",
        "spacing_top": 100,
        "spacing_bottom": 100,
        "color_scheme": "color__bg-body color__text",
        "color_border": "color__border-divider-1",
        "color_button": "btn btn--secondary",
        "style_border": "border--b-width",
        "row_size_desktop": "md:grid-cols-2",
        "row_size_mobile": "grid-cols-1",
        "layout_x_alignment": "text-center justify-center flex-col items-center",
        "visibility": ""
      }
    },
    "84c299e3-89f4-4122-ba7a-adec40bab641": {
      "type": "collection-grid",
      "blocks": {
        "d6c40f26-381a-43b1-aa93-467d35e8cd57": {
          "type": "collection",
          "settings": {
            "collection": "kartonnen-frietbakjes"
          }
        },
        "104b014d-6fe7-413f-bec5-a74ddd5fc3a3": {
          "type": "collection",
          "settings": {
            "collection": "toytrays"
          }
        },
        "29e0abd3-6337-4acb-81e9-f7e4c95a5271": {
          "type": "collection",
          "settings": {
            "collection": "toykits"
          }
        },
        "collection_ftGwaf": {
          "type": "collection",
          "settings": {
            "collection": ""
          }
        },
        "collection_rXAFVD": {
          "type": "collection",
          "settings": {
            "collection": ""
          }
        },
        "collection_tPRFtB": {
          "type": "collection",
          "settings": {
            "collection": ""
          }
        }
      },
      "block_order": [
        "d6c40f26-381a-43b1-aa93-467d35e8cd57",
        "104b014d-6fe7-413f-bec5-a74ddd5fc3a3",
        "29e0abd3-6337-4acb-81e9-f7e4c95a5271",
        "collection_ftGwaf",
        "collection_rXAFVD",
        "collection_tPRFtB"
      ],
      "disabled": true,
      "settings": {
        "heading": "Alle categorieën",
        "content": "",
        "button_label": "",
        "button_url": "",
        "spacing_top": 100,
        "spacing_bottom": 100,
        "color_scheme": "color__bg-body color__text",
        "color_border": "color__border-divider-1",
        "color_button": "btn btn--secondary",
        "style_border": "border--b-width",
        "row_size_desktop": "md:grid-cols-4",
        "row_size_mobile": "grid grid-cols-2",
        "layout_x_alignment": "justify-between",
        "visibility": "",
        "enable_collection_size_count": true
      }
    },
    "collection_slider_dH638W": {
      "type": "collection-slider",
      "blocks": {
        "collection_Eewm4q": {
          "type": "collection",
          "settings": {
            "collection": "toykits"
          }
        },
        "collection_DhQYLC": {
          "type": "collection",
          "settings": {
            "collection": "toytrays"
          }
        },
        "collection_FiFame": {
          "type": "collection",
          "settings": {
            "collection": "kidsboxen"
          }
        },
        "collection_KwXeie": {
          "type": "collection",
          "settings": {
            "collection": "aluminiumfolie"
          }
        },
        "collection_RtehXf": {
          "type": "collection",
          "settings": {
            "collection": "apet-vleeswarenschaaltjes"
          }
        },
        "collection_BFJMmm": {
          "type": "collection",
          "settings": {
            "collection": "bakpapier"
          }
        }
      },
      "block_order": [
        "collection_Eewm4q",
        "collection_DhQYLC",
        "collection_FiFame",
        "collection_KwXeie",
        "collection_RtehXf",
        "collection_BFJMmm"
      ],
      "settings": {
        "heading": "Alle categorieën",
        "content": "",
        "button_label": "",
        "button_url": "",
        "spacing_top": 100,
        "spacing_bottom": 100,
        "color_scheme": "color__bg-body color__text",
        "color_border": "color__border-divider-1",
        "color_button": "btn btn--tertiary",
        "style_border": "border--b-width",
        "layout_x_alignment": "justify-between",
        "visibility": "",
        "enable_collection_size_count": true
      }
    },
    "product_slider_FjtiUm": {
      "type": "product-slider",
      "blocks": {
        "card_RBRfnE": {
          "type": "card",
          "disabled": true,
          "settings": {
            "heading": "Block heading",
            "content": "<p>Describe a product, make announcements, or welcome customers to your store.<\/p>",
            "button_label": "Button",
            "button_url": "\/"
          }
        }
      },
      "block_order": [
        "card_RBRfnE"
      ],
      "settings": {
        "collection": "suikerriet-frietbakjes",
        "products_count": 16,
        "heading": "Hardlopers",
        "content": "",
        "button_label": "",
        "button_url": "",
        "spacing_top": 100,
        "spacing_bottom": 100,
        "color_scheme": "color__bg-body color__text",
        "color_border": "color__border-divider-1",
        "color_button": "btn btn--secondary",
        "style_border": "border--b-width",
        "layout_x_alignment": "justify-between",
        "visibility": ""
      }
    },
    "4957c6b2-3abe-4e8a-a342-c28fcddc4f97": {
      "type": "product-grid",
      "blocks": {
        "template--20644271554834__4957c6b2-3abe-4e8a-a342-c28fcddc4f97-card-1": {
          "type": "card",
          "disabled": true,
          "settings": {
            "heading": "Block heading",
            "content": "<p>Describe a product, make announcements, or inform customers about a promotion.<\/p>",
            "button_label": "Button",
            "button_url": "\/"
          }
        }
      },
      "block_order": [
        "template--20644271554834__4957c6b2-3abe-4e8a-a342-c28fcddc4f97-card-1"
      ],
      "disabled": true,
      "settings": {
        "collection": "suikerriet-frietbakjes",
        "products_count": 9,
        "heading": "Hardlopers",
        "content": "",
        "button_label": "Alle hardlopers",
        "button_url": "",
        "spacing_top": 100,
        "spacing_bottom": 100,
        "color_scheme": "color__bg-body color__text",
        "color_border": "color__border-divider-1",
        "color_button": "btn btn--secondary",
        "style_border": "border--b-width",
        "row_size_desktop": "md:grid-cols-4",
        "row_size_mobile": "grid grid-cols-2",
        "layout_x_alignment": "justify-between",
        "visibility": ""
      }
    },
    "d7e3b662-c368-4636-9d51-e4d12b8168f7": {
      "type": "product-slider",
      "disabled": true,
      "settings": {
        "collection": "aluminium-bakjes",
        "products_count": 4,
        "heading": "Andere Suggesties…",
        "content": "",
        "button_label": "",
        "button_url": "",
        "spacing_top": 100,
        "spacing_bottom": 100,
        "color_scheme": "color__bg-body color__text",
        "color_border": "color__border-divider-1",
        "color_button": "btn btn--secondary",
        "style_border": "border--b-width",
        "layout_x_alignment": "justify-between",
        "visibility": ""
      }
    },
    "96dcd7af-6180-401d-bf36-5aafc0ddf102": {
      "type": "content-grid",
      "blocks": {
        "template--20644271554834__96dcd7af-6180-401d-bf36-5aafc0ddf102-content-1": {
          "type": "content",
          "settings": {
            "heading": "",
            "content": "",
            "button_label": "",
            "button_url": "",
            "full_block_link": false,
            "image_featured": "shopify:\/\/shop_images\/building.png",
            "enable_autoplay": true,
            "enable_mute_toggle": true,
            "enable_loop": true,
            "spacing_top": 0,
            "spacing_bottom": 0,
            "enable_padding": true,
            "color_scheme": "color__bg-body color__text",
            "color_border": "!color__border-transparent",
            "color_text": "color__text",
            "color_button": "btn",
            "enable_gradient": false,
            "layout_y_alignment": "items-end content-end",
            "layout_x_alignment": "",
            "layout_row_span": "row-span-1",
            "layout_col_span": "col-span-1 md: md:col-span-1"
          }
        },
        "template--20644271554834__96dcd7af-6180-401d-bf36-5aafc0ddf102-content-6": {
          "type": "content",
          "settings": {
            "heading": "Over De Jong Disposables",
            "content": "<p>Al meer dan 35 jaar hebben wij ervaring met disposables. Ons familiebedrijf staat voor kwaliteit, betrouwbaarheid, innovatie en duurzaamheid. En dat tegen een scherpe prijs. <\/p>",
            "button_label": "Learn More",
            "button_url": "shopify:\/\/collections\/all",
            "full_block_link": false,
            "enable_autoplay": true,
            "enable_mute_toggle": true,
            "enable_loop": true,
            "spacing_top": 0,
            "spacing_bottom": 0,
            "enable_padding": true,
            "color_scheme": "color__bg-body color__text",
            "color_border": "color__border-divider-1",
            "color_text": "color__text",
            "color_button": "btn",
            "enable_gradient": false,
            "layout_y_alignment": "items-end content-end",
            "layout_x_alignment": "",
            "layout_row_span": "row-span-1",
            "layout_col_span": "col-span-1 md: md:col-span-1"
          }
        }
      },
      "block_order": [
        "template--20644271554834__96dcd7af-6180-401d-bf36-5aafc0ddf102-content-1",
        "template--20644271554834__96dcd7af-6180-401d-bf36-5aafc0ddf102-content-6"
      ],
      "settings": {
        "heading": "",
        "content": "",
        "button_label": "",
        "button_url": "",
        "spacing_top": 100,
        "spacing_bottom": 100,
        "color_scheme": "color__bg-overlay-1 color__text",
        "color_border": "color__border-divider-1",
        "color_button": "btn btn--secondary",
        "style_border": "border--b-width",
        "row_size_desktop": "md:grid-cols-2",
        "row_size_mobile": "grid-cols-1",
        "layout_x_alignment": "justify-between",
        "visibility": ""
      }
    },
    "153e1f9d-36b0-4e41-84cd-6510d2d62de1": {
      "type": "icon-grid",
      "blocks": {
        "template--20644271554834__153e1f9d-36b0-4e41-84cd-6510d2d62de1-icon-3": {
          "type": "icon",
          "settings": {
            "icon": "shopify:\/\/shop_images\/kwaliteit-prijs.svg",
            "icon_height": "h-14",
            "heading": "Kwaliteit & prijs",
            "content": "<p>Wij helpen u met producten van de hoogste kwaliteit voor de scherpste prijs.<\/p>",
            "enable_padding": true,
            "color_scheme": "color__bg-body color__text",
            "color_border": "!color__border-transparent",
            "layout_alignment": "flex-col",
            "layout_x_alignment": "text-center justify-center",
            "layout_row_span": "row-span-1",
            "layout_col_span": "col-span-1 md:col-span-1"
          }
        },
        "template--20644271554834__153e1f9d-36b0-4e41-84cd-6510d2d62de1-icon-2": {
          "type": "icon",
          "settings": {
            "icon": "shopify:\/\/shop_images\/icon-usp-reward.svg",
            "icon_height": "h-14",
            "heading": "Betrouwbaar",
            "content": "<p>Ons familiebedrijf is al meer dan 35 jaar wereldwijd actief. <\/p>",
            "enable_padding": true,
            "color_scheme": "color__bg-body color__text",
            "color_border": "!color__border-transparent",
            "layout_alignment": "flex-col",
            "layout_x_alignment": "text-center justify-center",
            "layout_row_span": "row-span-1",
            "layout_col_span": "col-span-1 md:col-span-1"
          }
        },
        "template--20644271554834__153e1f9d-36b0-4e41-84cd-6510d2d62de1-icon-1": {
          "type": "icon",
          "settings": {
            "icon": "shopify:\/\/shop_images\/icon-usp-shipping_1.svg",
            "icon_height": "h-14",
            "heading": "Verzending",
            "content": "<p>Vanaf € 250,- geen verzendkosten, levertijd circa 3 werkdagen.<br\/><\/p>",
            "enable_padding": true,
            "color_scheme": "color__bg-body color__text",
            "color_border": "!color__border-transparent",
            "layout_alignment": "flex-col",
            "layout_x_alignment": "text-center justify-center",
            "layout_row_span": "row-span-1",
            "layout_col_span": "col-span-1 md:col-span-1"
          }
        }
      },
      "block_order": [
        "template--20644271554834__153e1f9d-36b0-4e41-84cd-6510d2d62de1-icon-3",
        "template--20644271554834__153e1f9d-36b0-4e41-84cd-6510d2d62de1-icon-2",
        "template--20644271554834__153e1f9d-36b0-4e41-84cd-6510d2d62de1-icon-1"
      ],
      "settings": {
        "heading": "",
        "content": "",
        "button_label": "",
        "button_url": "",
        "spacing_top": 100,
        "spacing_bottom": 100,
        "color_scheme": "color__bg-body color__text",
        "color_border": "color__border-divider-1",
        "color_button": "btn btn--secondary",
        "style_border": "border--t-width",
        "row_size_desktop": "md:grid-cols-3",
        "row_size_mobile": "grid-cols-1",
        "layout_x_alignment": "justify-between",
        "visibility": ""
      }
    },
    "78a339b1-cd3c-4871-898d-b86e6dc91a94": {
      "type": "accordions",
      "blocks": {
        "template--20644271554834__78a339b1-cd3c-4871-898d-b86e6dc91a94-content-1": {
          "type": "content",
          "settings": {
            "title": "Vanaf welk bedrag worden er geen verzendkosten in rekening gebracht?",
            "content": "<p>In Nederland, België en Duitsland berekenen wij vanaf € 250,- exclusief btw geen verzendkosten, orders tot € 250,- worden belast met € 15,- exclusief btw aan verzendkosten.<\/p>",
            "icon": ""
          }
        },
        "template--20644271554834__78a339b1-cd3c-4871-898d-b86e6dc91a94-content-2": {
          "type": "content",
          "settings": {
            "title": "Kan ik mijn bestelling ook afhalen?",
            "content": "<p>U kunt uw bestelling zonder verzendkosten afhalen in Tynaarlo, dit kunt u aangeven tijdens het afrekenen.<\/p>",
            "icon": ""
          }
        },
        "template--20644271554834__78a339b1-cd3c-4871-898d-b86e6dc91a94-content-3": {
          "type": "content",
          "settings": {
            "title": "Verzending en levertijd",
            "content": "<p>Al onze goederen worden verzonden door een betrouwbare partner waar wij al jaren tevreden zaken mee doen, afhankelijk van de ordergrootte versturen wij onze goederen op europallets (80 x 120cm), halve pallets (80 x 60cm) of als losse colli(s).<br\/>Onze levertijden zijn na ontvangst van betaling en indien op voorraad ca. met 3 werkdagen, indien iets onverhoopt (tijdelijk) niet op voorraad is nemen wij zo spoedig mogelijk contact met u op voor een oplossing.<\/p>",
            "icon": ""
          }
        },
        "content_MwXGz8": {
          "type": "content",
          "settings": {
            "title": "Kan ik mijn bestelling op een latere datum ontvangen?",
            "content": "<p>Bij het afronden van uw order kunt u in het opmerkingen veld aangeven wanneer u de bestelling kunt ontvangen, met uitzondering van zaterdagen en zondagen. Indien wij niet aan deze leverdatum kunnen voldoen nemen wij contact met u op.<\/p>",
            "icon": ""
          }
        },
        "content_QcAmL9": {
          "type": "content",
          "settings": {
            "title": "Kan ik mijn bestelling volgen?",
            "content": "<p>Onze transporteur werkt met een track en trace systeem, de avond voor de dag van aflevering ontvangt u een e-mail van onze transporteur met daarin de link voor de track en trace omgeving.<\/p>",
            "icon": ""
          }
        },
        "content_eE9mmc": {
          "type": "content",
          "settings": {
            "title": "Zijn de prijzen inclusief of exclusief btw?",
            "content": "<p>Alle prijzen op de product en categorie pagina’s zijn exclusief btw, in uw winkelwagen ziet u het bedrag wat u aan btw moet betalen.<\/p>",
            "icon": ""
          }
        },
        "content_knWVDj": {
          "type": "content",
          "settings": {
            "title": "Zijn de Disposables ook te bedrukken met eigen logo?",
            "content": "<p>Praktisch het gehele assortiment is te bedrukken met eigen logo, neem vrijblijvend contact met ons op voor een fantastisch voorstel.<\/p>",
            "icon": ""
          }
        }
      },
      "block_order": [
        "template--20644271554834__78a339b1-cd3c-4871-898d-b86e6dc91a94-content-1",
        "template--20644271554834__78a339b1-cd3c-4871-898d-b86e6dc91a94-content-2",
        "template--20644271554834__78a339b1-cd3c-4871-898d-b86e6dc91a94-content-3",
        "content_MwXGz8",
        "content_QcAmL9",
        "content_eE9mmc",
        "content_knWVDj"
      ],
      "settings": {
        "heading": "FAQs",
        "content": "",
        "button_label": "Help Center",
        "button_url": "\/",
        "spacing_top": 100,
        "spacing_bottom": 100,
        "color_scheme": "color__bg-body color__text",
        "color_border": "color__border-divider-1",
        "color_button": "btn btn--secondary",
        "style_border": "border--b-width",
        "layout_x_alignment": "justify-between",
        "visibility": ""
      }
    }
  },
  "order": [
    "f96b8e1b-0fd4-4c65-856c-cdd01fe228cc",
    "2cb9d59b-242d-48e7-821a-ae61144186e8",
    "0aee11fe-16ff-4cae-924b-b6dc71c8827b",
    "1e9b6aa9-2f3a-4ca0-a7b2-65d5c9c14d5f",
    "84c299e3-89f4-4122-ba7a-adec40bab641",
    "collection_slider_dH638W",
    "product_slider_FjtiUm",
    "4957c6b2-3abe-4e8a-a342-c28fcddc4f97",
    "d7e3b662-c368-4636-9d51-e4d12b8168f7",
    "96dcd7af-6180-401d-bf36-5aafc0ddf102",
    "153e1f9d-36b0-4e41-84cd-6510d2d62de1",
    "78a339b1-cd3c-4871-898d-b86e6dc91a94"
  ]
}
